{"Exif":{"Lat":0,"Long":0,"Date":"2023-07-11T17:40:00+08:00","Tags":{"ApertureValue":1.69,"BrightnessValue":0,"ComponentsConfiguration":"","CustomRendered|int":"1","DateTimeDigitized|time.Time":"2023-07-11T17:40:00+08:00","DateTimeOriginal|time.Time":"2023-07-11T17:40:00+08:00","DateTime|time.Time":"2023-07-11T17:40:00+08:00","DigitalZoomRatio":1,"ExposureTime|*big.Rat":"191/500000","FNumber":1.8,"FileSource":"","FocalLength":5.58,"FocalLengthIn35mmFilm|int":"27","GainControl|int":"0","ISOSpeedRatings|int":"50","ImageDescription":"qrf","LightSource|int":"1","MaxApertureValue":1.69,"Orientation|int":"1","SceneCaptureType|int":"0","SceneType":"","ShutterSpeedValue":29.897300158814186,"Software":"Luminar Neo","SubSecTime":"000","SubSecTimeDigitized":"000","SubSecTimeOriginal":"000","SubjectDistanceRange|int":"0","YCbCrPositioning|int":"1"}}}
